<?xml version="1.0" encoding="UTF-8"?><document>
<id>304690</id>
<source_notice>302854</source_notice>
<status>1</status>
<general>
<procurement_code>DNP 2012/42</procurement_code>
<procurement_id>DNP 2012/42</procurement_id>
<main_cpv>
<code>85100000-0</code>
<code_num>85100000</code_num>
<type>3</type>
<lv>Veselības pakalpojumi.</lv>
<en>Health services</en>
<cpv_a>85</cpv_a>
<cpv_b>100000-0</cpv_b></main_cpv>
<name>Obligātās veselības pārbaude ESF projekta „Algotie pagaidu sabiedriskie darbi pašvaldībās” ietvaros</name>
<price_from>3000</price_from>
<price_to>20000</price_to>
<procurement_type>1</procurement_type>
<authority_id>22578</authority_id>
<authority_name>Dagdas novada pašvaldība</authority_name>
<authority_reg_num>90000041224</authority_reg_num>
<address>Alejas ielā 4</address>
<city>Dagda</city>
<zip_code>LV-5674</zip_code>
<country>1</country>
<procurement_year>2012</procurement_year>
<cpv_list></cpv_list>
<additional_cpv_list></additional_cpv_list></general>
<divided_in_parts>0</divided_in_parts>
<contract_name>Obligātās veselības pārbaude ESF projekta „Algotie pagaidu sabiedriskie darbi pašvaldībās” ietvaros</contract_name>
<place>Dagda, Dagdas novads</place>
<region>5</region>
<eu_fund>1</eu_fund>
<environment_req>0</environment_req>
<approval_date_stamp>1357732343</approval_date_stamp>
<eu_list>
<eu>
<eu_short>ESF</eu_short>
<eu_long>ESF projekts "Algotie pagaidu sabiedriskie darbi pašvaldībās" (paredzēts īstenot darbības programmas "Cilvēkresursi un nodarbinātība” papildinājuma 1.3.1.5. aktivitātes „Vietējo nodarbinātības veicināšanas pasākumu plānu ieviešanas atbalsts” otrās kārtas ietvaros") </eu_long></eu></eu_list>
<parts></parts>
<part_5_list>
<part_5>
<contract_nr>1</contract_nr>
<part_nr>1</part_nr>
<concluded_contract_name>Obligātās veselības pārbaude ESF projekta „Algotie pagaidu sabiedriskie darbi pašvaldībās” ietvaros</concluded_contract_name>
<decision_date>08/01/2013</decision_date>
<tender_num>1</tender_num>
<initial_price>14000</initial_price>
<initial_currency>1</initial_currency>
<contract_price_exact>14000</contract_price_exact>
<exact_currency>1</exact_currency>
<contract_price_from></contract_price_from>
<contract_price_to></contract_price_to>
<contract_with_vat>0</contract_with_vat>
<contract_vat_rate></contract_vat_rate>
<contract_currency></contract_currency>
<subcontracts></subcontracts>
<subcontract_price></subcontract_price>
<subcontract_currency></subcontract_currency>
<subcontract_proportion></subcontract_proportion>
<subcontract_unknown></subcontract_unknown>
<value_description></value_description>
<without_results></without_results>
<interrupted></interrupted>
<interrupt_info></interrupt_info>
<lower_price></lower_price>
<lower_currency></lower_currency>
<contract_count></contract_count>
<product_from_eu></product_from_eu>
<product_country></product_country>
<criteria_type></criteria_type>
<winner_with_variants></winner_with_variants>
<low_offers></low_offers>
<years_expenses></years_expenses>
<months_expenses></months_expenses>
<contract_price_exact_lvl></contract_price_exact_lvl>
<contract_price_exact_secret_lvl></contract_price_exact_secret_lvl>
<contract_price_exact_secret></contract_price_exact_secret>
<exact_currency_secret></exact_currency_secret>
<publicate_winner></publicate_winner>
<party_nr></party_nr>
<party_nr_secret></party_nr_secret>
<winner_list>
<winner>
<winner_name>Dagdas novada PI "Veselības un sociālo pakalpojumu centrs "DAGDA""</winner_name>
<winner_reg_num>90009226858</winner_reg_num>
<winner_address>Brīvības iela 29</winner_address>
<winner_city>Dagdas novads</winner_city>
<winner_zip_code>5674</winner_zip_code>
<winner_country>1</winner_country>
<winner_phone></winner_phone>
<winner_fax></winner_fax>
<winner_email></winner_email>
<winner_url></winner_url></winner></winner_list></part_5></part_5_list>
<authority_name>Dagdas novada pašvaldība</authority_name>
<address>Alejas ielā 4</address>
<authority_reg_num>90000041224</authority_reg_num>
<zip_code>LV-5674</zip_code>
<city>Dagda</city>
<country>1</country>
<middleman>0</middleman>
<creation_date>09/01/2013</creation_date>
<creation_date_stamp>1357731988</creation_date_stamp>
<authority_id>22578</authority_id>
<contactplaces>
<contactplace>
<type>Galvenais kontaktpunkts</type>
<name>Dagdas novada pašvaldība</name>
<short_name>DNP</short_name>
<reg_num></reg_num>
<address></address>
<city></city>
<zip_code></zip_code>
<country></country>
<place>Juridiskā nodaļa</place>
<person>Kristīne Murāne</person>
<phone>65681712</phone>
<fax>65681710</fax>
<email>juridiska.nodala@dagda.lv</email>
<url>http://www.dagda.lv</url>
<url_client>http://www.dagda.lv</url_client>
<procurement_doc_url></procurement_doc_url>
<tender_submit_url></tender_submit_url></contactplace></contactplaces>
<service_types>25</service_types>
<description>Obligātās veselības pārbaude ESF projekta „Algotie pagaidu sabiedriskie darbi pašvaldībās” ietvaros</description>
<price_exact>14000</price_exact>
<currency>1</currency>
<type>notice_concluded_contract</type>
<approval_date>09/01/2013</approval_date>
<publication_date>09/01/2013</publication_date>
<publication_date_stamp>1357732343</publication_date_stamp>
<statistics_version>4</statistics_version>
<price_exact_eur>19920.32</price_exact_eur>
<eur_conv_version>2</eur_conv_version>
<global_winner_title>Dagdas novada PI Veselības un sociālo pakalpojumu centrs DAGDA</global_winner_title>
<global_winner_reg_num>90009226858</global_winner_reg_num>
<set_global_data_version>1</set_global_data_version>
<populate_iub_winners>3</populate_iub_winners>
<archived>1</archived></document>